<?xml version="1.0" encoding="UTF-8"?>
<objects serializationModel="Studio.02.03.00">
	<object class="AudioFile" id="{9fb53c1f-2659-4410-afe9-d7cc81a28f0a}">
		<property name="assetPath">
			<value>one shoty/jump/stone/jump_stone_4.flac</value>
		</property>
		<property name="frequencyInKHz">
			<value>48</value>
		</property>
		<property name="channelCount">
			<value>2</value>
		</property>
		<property name="length">
			<value>1.0625</value>
		</property>
		<relationship name="masterAssetFolder">
			<destination>{cb4fa515-17a0-467a-b7d7-a8a452b9506d}</destination>
		</relationship>
	</object>
</objects>
